methtuple/__init__.py
methtuple/funcs.py
methtuple/mtuple.py
methtuple/scripts/methtuple
methtuple/tests/__init__.py
methtuple-1.8.0.data/scripts/methtuple
methtuple-1.8.0.dist-info/LICENSE.md
methtuple-1.8.0.dist-info/METADATA
methtuple-1.8.0.dist-info/WHEEL
methtuple-1.8.0.dist-info/top_level.txt
methtuple-1.8.0.dist-info/RECORD
