Metadata-Version: 2.1
Name: methtuple
Version: 1.8.0
Summary: methtuple
Home-page: https://github.com/PeteHaitch/methtuple
Author: Peter Hickey
Author-email: peter.hickey@gmail.com
License: MIT
Keywords: bisulfite sequencing methylation bismark bioinformatics
Platform: UNKNOWN
Classifier: Programming Language :: Python :: 3.6
Classifier: Programming Language :: Python :: 3.7
Classifier: Programming Language :: Python :: 3.8
Classifier: Programming Language :: Python :: 3.9
Classifier: License :: OSI Approved :: MIT License
Classifier: Topic :: Scientific/Engineering :: Bio-Informatics
License-File: LICENSE.md
Requires-Dist: pysam (>=0.8.4)
